cores/__init__.py
cores/__version__.py
cores/baserepo.py
cores/core.py
cores/notification/__init__.py
cores/notification/notification.py
cores/notification/notificationcenter.py
cores/notification/unitest.py
pycores/__init__.py
pycores/__version__.py
pycores/baserepo.py
pycores/core.py
pycores/notification/__init__.py
pycores/notification/notification.py
pycores/notification/notificationcenter.py
pycores/notification/unitest.py
pycores-0.1.12.dist-info/METADATA
pycores-0.1.12.dist-info/RECORD
pycores-0.1.12.dist-info/WHEEL
pycores-0.1.12.dist-info/top_level.txt
